repo_guide/__init__.py
repo_guide/__main__.py
repo_guide/cli.py
repo_guide-0.7.0.dist-info/METADATA
repo_guide-0.7.0.dist-info/WHEEL
repo_guide-0.7.0.dist-info/entry_points.txt
repo_guide-0.7.0.dist-info/licenses/LICENSE
repo_guide-0.7.0.dist-info/RECORD
