Metadata-Version: 2.4
Name: repo-guide
Version: 0.7.0
Summary: Use AI to generate guides to code repositories.
Project-URL: Homepage, https://github.com/wolfmanstout/repo-guide
Project-URL: Changelog, https://github.com/wolfmanstout/repo-guide/releases
Project-URL: Issues, https://github.com/wolfmanstout/repo-guide/issues
Project-URL: CI, https://github.com/wolfmanstout/repo-guide/actions
Author: James Stout
License-File: LICENSE
Classifier: License :: OSI Approved :: Apache Software License
Requires-Python: >=3.11
Requires-Dist: bleach-allowlist>=1.0.3
Requires-Dist: bleach>=6.2.0
Requires-Dist: click
Requires-Dist: gitpython>=3.1.43
Requires-Dist: llm-gemini>=0.10
Requires-Dist: llm>=0.19a0
Requires-Dist: mkdocs-material>=9.5.46
Requires-Dist: mkdocs>=1.6.1
Requires-Dist: tiktoken>=0.8.0
Requires-Dist: tqdm>=4.67.1
Provides-Extra: magika
Requires-Dist: magika>=0.6.0rc3; extra == 'magika'
